{
  "bubble_state": "positive",
  "usdt_bubble_state": "positive",
  "last_raw": {
    "usd_raw": "1570000",
    "aed_raw": "427440",
    "usdt_raw": "1605100"
  },
  "updated_at": "1405/01/18 07:45:25",
  "portfolio": {
    "initial_cash_irr": 1000000000.0,
    "cash_irr": 1061156949.996943,
    "usdt_qty": 0.0,
    "position_open": false,
    "entry_price": null,
    "entry_value_irr": null,
    "trade_count": 30,
    "realized_pnl_irr": 115054667.567195,
    "last_action": "SELL",
    "last_action_time": "1405/01/16 04:21:38"
  }
}